LICENSE
MANIFEST.in
README.md
cumulus_logger.py
pyproject.toml
requirements.txt
run_cumulus_task.py
setup.py
cumulus_message_adapter_python.egg-info/PKG-INFO
cumulus_message_adapter_python.egg-info/SOURCES.txt
cumulus_message_adapter_python.egg-info/dependency_links.txt
cumulus_message_adapter_python.egg-info/requires.txt
cumulus_message_adapter_python.egg-info/top_level.txt
example/README.md
example/requirements.txt
example/task.py
tests/helpers.py
tests/test.py
tests/test_env_var.py
tests/test_logger.py