Metadata-Version: 2.4
Name: cumulus-message-adapter-python
Version: 2.4.0
Summary: A handler library for cumulus tasks written in python
Home-page: https://github.com/cumulus-nasa/cumulus-message-adapter-python
Author: Cumulus Authors
Author-email: info@developmentseed.org
License: Copyright © 2018 United States Government as represented by the Administrator of the National Aeronautics and Space Administration. All Rights Reserved.
Requires-Python: ~=3.12, <4.0
License-File: LICENSE
Requires-Dist: cumulus-message-adapter~=2.0.5
Provides-Extra: dev
Requires-Dist: nose2; extra == "dev"
Requires-Dist: mock; extra == "dev"
Dynamic: author-email
Dynamic: home-page
Dynamic: license-file
Dynamic: requires-python
